RigExpert/RigExpert.py
RigExpert/__init__.py
RigExpert/_version.py
rigexpert-0.1.3.dist-info/licenses/LICENSE
rigexpert-0.1.3.dist-info/METADATA
rigexpert-0.1.3.dist-info/WHEEL
rigexpert-0.1.3.dist-info/entry_points.txt
rigexpert-0.1.3.dist-info/top_level.txt
rigexpert-0.1.3.dist-info/RECORD
