Metadata-Version: 2.4
Name: RigExpert
Version: 0.1.3
Summary: Draw Smith charts, VSWR graphs and more from RigExpert or NanoVNA .s1p files.
Author: Fred C.
License: BSD 3-Clause License
Project-URL: Homepage, https://github.com/0x9900/RigExpert
Project-URL: Tracker, https://github.com/0x9900/RigExpert/issues
Classifier: Intended Audience :: End Users/Desktop
Classifier: Intended Audience :: Telecommunications Industry
Classifier: Operating System :: MacOS
Classifier: Operating System :: POSIX :: Linux
Classifier: Programming Language :: Python
Classifier: Programming Language :: Python :: 3.10
Classifier: Programming Language :: Python :: 3.11
Classifier: Programming Language :: Python :: 3.12
Requires-Python: >=3.10
License-File: LICENSE
Requires-Dist: matplotlib
Requires-Dist: numpy
Requires-Dist: scikit-rf
Provides-Extra: dev
Requires-Dist: build; extra == "dev"
Requires-Dist: flake8; extra == "dev"
Requires-Dist: isort; extra == "dev"
Requires-Dist: pre-commit; extra == "dev"
Requires-Dist: pylint; extra == "dev"
Requires-Dist: mypy; extra == "dev"
Dynamic: license-file
